mypkgasim/__init__.py
mypkgasim-0.1.0.dist-info/WHEEL
mypkgasim-0.1.0.dist-info/METADATA
mypkgasim-0.1.0.dist-info/RECORD
